netbox_diagram/__init__.py
netbox_diagram/navigation.py
netbox_diagram/signals.py
netbox_diagram/template_content.py
netbox_diagram/urls.py
netbox_diagram/worker.py
netbox_diagram/api/__init__.py
netbox_diagram/api/urls.py
netbox_diagram/api/serializers/__init__.py
netbox_diagram/api/serializers/diagram.py
netbox_diagram/api/views/__init__.py
netbox_diagram/api/views/diagram.py
netbox_diagram/filtersets/__init__.py
netbox_diagram/filtersets/diagram.py
netbox_diagram/forms/__init__.py
netbox_diagram/forms/diagram.py
netbox_diagram/migrations/0001_initial.py
netbox_diagram/migrations/0002_alter_diagram_options_and_more.py
netbox_diagram/migrations/__init__.py
netbox_diagram/models/__init__.py
netbox_diagram/models/diagram.py
netbox_diagram/models/tabs.py
netbox_diagram/static/netbox_diagram/css/diagram.css
netbox_diagram/static/netbox_diagram/js/d3.v7.min.js
netbox_diagram/tables/__init__.py
netbox_diagram/tables/diagram.py
netbox_diagram/templates/netbox_diagram/diagram.html
netbox_diagram/templates/netbox_diagram/diagramassociation.html
netbox_diagram/templates/netbox_diagram/diagramassociation_edit.html
netbox_diagram/templates/netbox_diagram/diagramtab.html
netbox_diagram/templates/netbox_diagram/sync_button.html
netbox_diagram/templates/netbox_diagram/generic/base.html
netbox_diagram/templates/netbox_diagram/panels/diagrams.html
netbox_diagram/tests/__init__.py
netbox_diagram/tests/test_api.py
netbox_diagram/tests/test_filtersets.py
netbox_diagram/tests/test_forms.py
netbox_diagram/tests/test_models.py
netbox_diagram/tests/test_utils.py
netbox_diagram/tests/test_views.py
netbox_diagram/tests/test_worker.py
netbox_diagram/utils/__init__.py
netbox_diagram/utils/diagram.py
netbox_diagram/views/__init__.py
netbox_diagram/views/diagram.py
netbox_diagram/views/diagramdata.py
netbox_diagram/views/jobs.py
netbox_diagram/views/tabs.py
netbox_diagram-0.0.2.dist-info/licenses/LICENSE
netbox_diagram-0.0.2.dist-info/METADATA
netbox_diagram-0.0.2.dist-info/WHEEL
netbox_diagram-0.0.2.dist-info/top_level.txt
netbox_diagram-0.0.2.dist-info/RECORD
