Metadata-Version: 2.4
Name: netbox_diagram
Version: 0.0.2
Summary: Diagrams based on Netbox Devices and Circuits
Author-email: Netbox Diagram <netboxdiagram@gmail.com>
License-Expression: MIT
Project-URL: Homepage, https://github.com/netboxdiagram/netbox_diagram
Project-URL: Bug Tracker, https://github.com/netboxdiagram/netbox_diagram/issues/
Keywords: netbox,netbox-plugin,diagram
Classifier: Programming Language :: Python :: 3
Classifier: Operating System :: OS Independent
Requires-Python: >=3.10
License-File: LICENSE
Dynamic: license-file
